MANIFEST.in
README.rst
setup.cfg
setup.py
maya_signatures/__init__.py
maya_signatures/cli.py
maya_signatures/version.py
maya_signatures/commands/__init__.py
maya_signatures/commands/base.py
maya_signatures/commands/cache.py
maya_signatures/commands/scrape.py
tests/test_scrape.py
tests/test_scrape.pyc