Metadata-Version: 1.1
Name: maya-cmds-help
Version: 0.6.3
Summary: A module and command line tool that scrapes the online maya help docs to query an input maya.cmds command (or build stubs) for its signature in Python.
Home-page: https://github.com/andresmweber/maya-cmds-help.git
Author: Andres Weber
Author-email: andresmweber@gmail.com
License: MIT
Keywords: cli,maya,stubs,stub,commands,maya.cmds,autodesk
Platform: UNKNOWN
Classifier: Intended Audience :: Developers
Classifier: Topic :: Utilities
Classifier: License :: Public Domain
Classifier: Natural Language :: English
Classifier: Operating System :: OS Independent
Classifier: Programming Language :: Python :: 3
